SetupGenerator
