Metadata-Version: 2.1
Name: hoy-setup-generator
Version: 1.1
Summary: Pequena biblioteca para criar um setup.py rápido.
Home-page: https://github.com/Hoyasumii/SetupGenerator.git
Author: Alan Reis Anjos
Author-email: alanreisanjo@gmail.com
License: GPL-3.0 license
License-File: LICENSE
Requires-Dist: hoy-typed-input==1.1
Requires-Dist: hoyl-keyboard-manager==1.0.1
Requires-Dist: keyboard==0.13.5
Requires-Dist: python-slugify==8.0.1
Requires-Dist: setuptools==69.0.3
Requires-Dist: text-unidecode==1.3
